setup.py
TkGame/GameObject.py
TkGame/GameScreen.py
TkGame/__init__.py
TkGame/soundmaker.py
TkGame.egg-info/PKG-INFO
TkGame.egg-info/SOURCES.txt
TkGame.egg-info/dependency_links.txt
TkGame.egg-info/requires.txt
TkGame.egg-info/top_level.txt
TkGame/images/__init__.py